ejtraderCT/__init__.py
ejtraderCT/api/Symbol.py
ejtraderCT/api/__init__.py
ejtraderCT/api/buffer.py
ejtraderCT/api/ctrader.py
ejtraderCT/api/fix.py
ejtraderCT/api/math.py
ejtraderCT-1.1.13.dist-info/LICENSE
ejtraderCT-1.1.13.dist-info/METADATA
ejtraderCT-1.1.13.dist-info/WHEEL
ejtraderCT-1.1.13.dist-info/top_level.txt
ejtraderCT-1.1.13.dist-info/RECORD
