Metadata-Version: 2.1
Name: ejtraderCT
Version: 1.1.13
Summary: Ctrader Fix API
Home-page: https://ejtraderCT.readthedocs.io/
Download-URL: https://ejtrader.com
Author: Emerson Pedroso & Douglas Barros
Author-email: support@ejtrader.com
License: MIT License
Project-URL: Bug Reports, https://github.com/ejtraderLabs/ejtraderCT/issues
Project-URL: Source, https://github.com/ejtraderLabs/ejtraderCT
Project-URL: Documentation, https://ejtraderCT.readthedocs.io/
Keywords: ctrader,fix-api,historical-data,financial-data,stocks,funds,etfs,indices,currency crosses,bonds,commodities,crypto currencies
Classifier: Programming Language :: Python :: 3 :: Only
Classifier: Programming Language :: Python :: 3.5
Classifier: Programming Language :: Python :: 3.6
Classifier: Programming Language :: Python :: 3.7
Classifier: Programming Language :: Python :: 3.8
Classifier: License :: OSI Approved :: MIT License
Classifier: Intended Audience :: Developers
Classifier: Topic :: Office/Business :: Financial
Classifier: Topic :: Office/Business :: Financial :: Investment
Classifier: Topic :: Scientific/Engineering :: Information Analysis
Classifier: Topic :: Software Development :: Libraries
Requires-Python: >=3
License-File: LICENSE
